json2png_annotation/__init__.py
json2png_annotation/cli.py
json2png_annotation/converter.py
json2png_annotation-0.1.0.dist-info/licenses/LICENSE
json2png_annotation-0.1.0.dist-info/METADATA
json2png_annotation-0.1.0.dist-info/WHEEL
json2png_annotation-0.1.0.dist-info/entry_points.txt
json2png_annotation-0.1.0.dist-info/top_level.txt
json2png_annotation-0.1.0.dist-info/RECORD
