Metadata-Version: 2.4
Name: json2png-annotation
Version: 0.1.0
Summary: A library for converting JSON annotation files to PNG masks
Home-page: https://github.com/nguyentran4896/json2png-annotation
Author: Nguyen Tran
Author-email: nguyentran4896@gmail.com
Classifier: Programming Language :: Python :: 3
Classifier: License :: OSI Approved :: MIT License
Classifier: Operating System :: OS Independent
Requires-Python: >=3.6
License-File: LICENSE
Requires-Dist: Pillow>=8.0.0
Dynamic: author
Dynamic: author-email
Dynamic: classifier
Dynamic: description
Dynamic: description-content-type
Dynamic: home-page
Dynamic: license-file
Dynamic: requires-dist
Dynamic: requires-python
Dynamic: summary
